AUTHORS
LICENSE
MANIFEST.in
README.md
requirements-min-django.txt
requirements-test.txt
requirements.txt
setup.py
django_feedz.egg-info/PKG-INFO
django_feedz.egg-info/SOURCES.txt
django_feedz.egg-info/dependency_links.txt
django_feedz.egg-info/not-zip-safe
django_feedz.egg-info/requires.txt
django_feedz.egg-info/top_level.txt
feedz/__init__.py
feedz/admin.py
feedz/conf.py
feedz/exceptions.py
feedz/feedutil.py
feedz/importers.py
feedz/maintenance.py
feedz/managers.py
feedz/models.py
feedz/optimization.py
feedz/tasks.py
feedz/utils.py
feedz/backends/__init__.py
feedz/backends/database.py
feedz/locale/ar/LC_MESSAGES/django.mo
feedz/locale/ar/LC_MESSAGES/django.po
feedz/locale/de/LC_MESSAGES/django.mo
feedz/locale/de/LC_MESSAGES/django.po
feedz/locale/en/LC_MESSAGES/django.mo
feedz/locale/en/LC_MESSAGES/django.po
feedz/locale/es/LC_MESSAGES/django.mo
feedz/locale/es/LC_MESSAGES/django.po
feedz/locale/fr/LC_MESSAGES/django.mo
feedz/locale/fr/LC_MESSAGES/django.po
feedz/locale/id/LC_MESSAGES/django.mo
feedz/locale/id/LC_MESSAGES/django.po
feedz/locale/ja/LC_MESSAGES/django.mo
feedz/locale/ja/LC_MESSAGES/django.po
feedz/locale/jp/LC_MESSAGES/django.mo
feedz/locale/jp/LC_MESSAGES/django.po
feedz/locale/ko/LC_MESSAGES/django.mo
feedz/locale/ko/LC_MESSAGES/django.po
feedz/locale/no/LC_MESSAGES/django.mo
feedz/locale/no/LC_MESSAGES/django.po
feedz/locale/pl/LC_MESSAGES/django.mo
feedz/locale/pl/LC_MESSAGES/django.po
feedz/locale/pt/LC_MESSAGES/django.mo
feedz/locale/pt/LC_MESSAGES/django.po
feedz/locale/pt_BR/LC_MESSAGES/django.mo
feedz/locale/pt_BR/LC_MESSAGES/django.po
feedz/locale/ru/LC_MESSAGES/django.mo
feedz/locale/ru/LC_MESSAGES/django.po
feedz/locale/sla/LC_MESSAGES/django.mo
feedz/locale/sla/LC_MESSAGES/django.po
feedz/locale/sr/LC_MESSAGES/django.mo
feedz/locale/sr/LC_MESSAGES/django.po
feedz/locale/tr/LC_MESSAGES/django.mo
feedz/locale/tr/LC_MESSAGES/django.po
feedz/locale/vi/LC_MESSAGES/django.mo
feedz/locale/vi/LC_MESSAGES/django.po
feedz/locale/zh/LC_MESSAGES/django.mo
feedz/locale/zh/LC_MESSAGES/django.po
feedz/locale/zh_CN/LC_MESSAGES/django.mo
feedz/locale/zh_CN/LC_MESSAGES/django.po
feedz/locale/zh_TW/LC_MESSAGES/django.mo
feedz/locale/zh_TW/LC_MESSAGES/django.po
