Metadata-Version: 1.1
Name: django-feedz
Version: 2.1.6
Summary: A Django model for analyzing RSS/Atom feeds.
Home-page: https://github.com/chrisspen/django-feedz
Author: Chris Spencer
Author-email: chrisspen@gmail.com
License: BSD
Platform: UNKNOWN
Classifier: Environment :: Web Environment
Classifier: Intended Audience :: Developers
Classifier: License :: OSI Approved :: MIT License
Classifier: Operating System :: OS Independent
Classifier: Programming Language :: Python
Classifier: Programming Language :: Python :: 3.3
Classifier: Programming Language :: Python :: 3.4
Classifier: Programming Language :: Python :: 3.5
Classifier: Programming Language :: Python :: 3.6
Classifier: Framework :: Django
